lauterbach/trace32/doxypractice/__init__.py
lauterbach/trace32/doxypractice/__main__.py
lauterbach/trace32/doxypractice/__version__.py
lauterbach/trace32/doxypractice/doxypractice.py
lauterbach_trace32_doxypractice-1.0.1.dist-info/licenses/LICENSES/MIT.txt
lauterbach_trace32_doxypractice-1.0.1.dist-info/METADATA
lauterbach_trace32_doxypractice-1.0.1.dist-info/WHEEL
lauterbach_trace32_doxypractice-1.0.1.dist-info/entry_points.txt
lauterbach_trace32_doxypractice-1.0.1.dist-info/top_level.txt
lauterbach_trace32_doxypractice-1.0.1.dist-info/RECORD
