Metadata-Version: 2.4
Name: lauterbach-trace32-doxypractice
Version: 1.0.1
Summary: Doxygen Filter for Lauterbach TRACE32 Scripts
Author-email: Lauterbach GmbH <support@lauterbach.com>
Maintainer-email: Lauterbach GmbH <support@lauterbach.com>
License-Expression: MIT
Project-URL: Homepage, https://www.lauterbach.com
Project-URL: Repository, https://gitlab.com/lauterbach/doxypractice
Project-URL: Issues, https://support.lauterbach.com/
Project-URL: Changelog, https://gitlab.com/lauterbach/doxypractice/-/blob/release/CHANGELOG.md
Classifier: Programming Language :: Python :: 3
Classifier: Programming Language :: Python :: 3.10
Classifier: Operating System :: OS Independent
Classifier: Topic :: Software Development :: Debuggers
Classifier: Intended Audience :: Developers
Requires-Python: >=3.10
License-File: LICENSES/MIT.txt
Requires-Dist: chardet>=5.2.0
Requires-Dist: tree-sitter>=v0.25.0
Requires-Dist: tree-sitter-t32>=5.5.0
Provides-Extra: dev
Requires-Dist: mypy; extra == "dev"
Requires-Dist: pre-commit; extra == "dev"
Requires-Dist: ruff; extra == "dev"
Requires-Dist: twine; extra == "dev"
Requires-Dist: types-setuptools; extra == "dev"
Provides-Extra: test
Requires-Dist: coverage; extra == "test"
Requires-Dist: pytest; extra == "test"
Requires-Dist: pytest-mock; extra == "test"
Dynamic: license-file
